Metadata-Version: 2.1
Name: pydatatable
Version: 1.2
Summary: Python library made to display graphical tables from the given data.
Home-page: https://github.com/Sid72020123/pydatatable
Author: Siddhesh Chavan
Author-email: siddheshchavan2020@gmail.com
License: MIT
Keywords: table-making-module
Platform: UNKNOWN
Classifier: Development Status :: 5 - Production/Stable
Classifier: Intended Audience :: Education
Classifier: Operating System :: Microsoft :: Windows :: Windows 10
Classifier: License :: OSI Approved :: MIT License
Classifier: Programming Language :: Python :: 3
